{
  "name": "土入りバケツ",
  "read_by_default": "true",
  "icon": "dynamictrees:dirt_bucket",
  "category": "dynamictrees:mechanics",
  "sortnum": 1,
  "pages": [
    {
      "type": "spotlight",
      "item": "dynamictrees:dirt_bucket",
      "title": "土入りバケツ",
      "link_recipe": true,
      "text": "土入りバケツは種子を苗木に変換したり、その逆を行う為のものです。$(br2)作業台に土入りバケツと種子または苗木を置くことで変換できます。このレシピは不定形です。"
    },
    {
      "type": "crafting",
      "title": "土入りバケツ",
      "anchor": "dirt_bucket",
      "recipe": "dynamictrees:dirt_bucket",
      "text": "土入りバケツを作るには、土ブロックとバケツを組み合わせるだけです。$(br2)必要であれば、地面を右クリックしてバケツを空にすることができます。"
    },
    {
      "type": "crafting",
      "title": "種子から苗木へ",
      "recipe": "dynamictrees:oak_seed_to_minecraft_oak_sapling",
      "recipe2": "dynamictrees:minecraft_oak_sapling_to_oak_seed"
    },
    {
      "type": "crafting",
      "title": "果実から種子へ",
      "recipe": "dynamictrees:minecraft_apple_to_apple_oak_seed",
      "text": "果樹は種子を落としませんが、果実から種子を得ることができます。"
    }
  ]
}
